MOLLUSC_SLT-1.0.0.data/scripts/run_mollusc.py
problin_libs/EM_solver.py
problin_libs/ML_solver.py
problin_libs/SpaLin_solver.py
problin_libs/Spatial_Division_solver.py
problin_libs/Topology_search.py
problin_libs/Topology_search_parallel.py
problin_libs/Virtual_solver.py
problin_libs/__init__.py
problin_libs/distance_based_lib.py
problin_libs/lca_lib.py
problin_libs/plot_lib.py
problin_libs/sequence_lib.py
problin_libs/sim_lib.py
unit_tests/__init__.py
unit_tests/unit_tests_EMSolver.py
unit_tests/unit_tests_MLSolver.py
unit_tests/unit_tests_Simulator.py
unit_tests/unit_tests_SpaLinSolver.py
unit_tests/unit_tests_TopoSearch.py
unit_tests/unit_tests_TopoSearchParallel.py
unit_tests/utils.py
MOLLUSC_SLT-1.0.0.dist-info/LICENSE
MOLLUSC_SLT-1.0.0.dist-info/METADATA
MOLLUSC_SLT-1.0.0.dist-info/WHEEL
MOLLUSC_SLT-1.0.0.dist-info/entry_points.txt
MOLLUSC_SLT-1.0.0.dist-info/top_level.txt
MOLLUSC_SLT-1.0.0.dist-info/zip-safe
MOLLUSC_SLT-1.0.0.dist-info/RECORD
